{
	"astFolder": {
		"path": "/Users/utilisateur/Documents/these/cpx-codewars/dist/genese-cpx/src/core/mocks/whole-file/",
		"astFiles": [
			{
				"name": "whole-file.js",
				"text": "const b = 3;\nfunction first() {\n    return 2;\n}\nfunction second(a) {\n    return a;\n}\n",
				"astNode": {
					"end": 85,
					"kind": "SourceFile",
					"pos": 0,
					"start": 0,
					"children": [
						{
							"end": 12,
							"kind": "VariableStatement",
							"pos": 0,
							"start": 0,
							"type": "NumericLiteral",
							"children": [
								{
									"end": 11,
									"kind": "VariableDeclarationList",
									"pos": 0,
									"start": 0,
									"children": [
										{
											"end": 11,
											"kind": "VariableDeclaration",
											"pos": 5,
											"start": 6,
											"children": [
												{
													"end": 7,
													"kind": "Identifier",
													"name": "b",
													"pos": 5,
													"start": 6
												},
												{
													"end": 11,
													"kind": "Literal",
													"pos": 9,
													"start": 10
												}
											]
										}
									]
								}
							]
						},
						{
							"end": 47,
							"kind": "FunctionDeclaration",
							"name": "first",
							"pos": 12,
							"start": 13,
							"children": [
								{
									"end": 27,
									"kind": "Identifier",
									"name": "first",
									"pos": 21,
									"start": 22
								},
								{
									"end": 47,
									"kind": "Block",
									"pos": 29,
									"start": 30,
									"children": [
										{
											"end": 45,
											"kind": "Keyword",
											"pos": 31,
											"start": 36,
											"children": [
												{
													"end": 44,
													"kind": "Literal",
													"pos": 42,
													"start": 43
												}
											]
										}
									]
								}
							]
						},
						{
							"end": 84,
							"kind": "FunctionDeclaration",
							"name": "second",
							"pos": 47,
							"start": 48,
							"children": [
								{
									"end": 63,
									"kind": "Identifier",
									"name": "second",
									"pos": 56,
									"start": 57
								},
								{
									"end": 65,
									"kind": "Parameter",
									"name": "a",
									"pos": 64,
									"start": 64,
									"children": [
										{
											"end": 65,
											"kind": "Identifier",
											"name": "a",
											"pos": 64,
											"start": 64
										}
									]
								},
								{
									"end": 84,
									"kind": "Block",
									"pos": 66,
									"start": 67,
									"children": [
										{
											"end": 82,
											"kind": "Keyword",
											"pos": 68,
											"start": 73,
											"children": [
												{
													"end": 81,
													"kind": "Identifier",
													"name": "a",
													"pos": 79,
													"start": 80
												}
											]
										}
									]
								}
							]
						},
						{
							"end": 85,
							"kind": "EndOfFileToken",
							"pos": 84,
							"start": 85
						}
					]
				}
			}
		]
	}
}